handit_ai-1.0.13.dist-info/METADATA
handit_ai-1.0.13.dist-info/WHEEL
handit_ai/__init__.py
handit_ai/__pycache__/__init__.cpython-310.pyc
handit_ai/__pycache__/__init__.cpython-313.pyc
handit_ai/__pycache__/fastapi.cpython-310.pyc
handit_ai/__pycache__/fastapi.cpython-313.pyc
handit_ai/fastapi.py
handit_ai/langchain.py
handit_core/__init__.py
handit_core/__pycache__/__init__.cpython-310.pyc
handit_core/__pycache__/__init__.cpython-313.pyc
handit_core/__pycache__/bedrock_instrumentation.cpython-312.pyc
handit_core/__pycache__/bedrock_instrumentation.cpython-313.pyc
handit_core/__pycache__/circuit_breaker.cpython-313.pyc
handit_core/__pycache__/http_instrumentation.cpython-310.pyc
handit_core/__pycache__/http_instrumentation.cpython-313.pyc
handit_core/__pycache__/openai_instrumentation.cpython-310.pyc
handit_core/__pycache__/openai_instrumentation.cpython-313.pyc
handit_core/bedrock_instrumentation.py
handit_core/handit_core_native.cpython-312-darwin.so
handit_core/http_instrumentation.py
handit_core/langchain_instrumentation.py
handit_core/openai_instrumentation.py
handit_ai-1.0.13.dist-info/RECORD
